aug_img/__init__.py
aug_img/imgaug.py
aug_img-0.1.2.dist-info/METADATA
aug_img-0.1.2.dist-info/WHEEL
aug_img-0.1.2.dist-info/top_level.txt
aug_img-0.1.2.dist-info/RECORD
