Metadata-Version: 2.1
Name: aug-img
Version: 0.1.2
Summary: package test use a simple image precessing example
Home-page: UNKNOWN
Author: chloejay
Author-email: ji.jie@edhec.com
License: MIT
Platform: UNKNOWN
Requires-Dist: numpy (>=1.15)
Requires-Dist: Pillow
Requires-Dist: pandas
Requires-Dist: matplotlib
Requires-Dist: scikit-image (>=0.14.2)
Requires-Dist: opencv-python-headless
